aquacrop/__init__.py
aquacrop/core.py
aquacrop/data/CP.dat
aquacrop/data/CP.st
"aquacrop/data/CP_EC-EARTH[CP,RCP45,2021-2040]WG.dat"
"aquacrop/data/CP_EC-EARTH[CP,RCP45,2041-2060]WG.dat"
"aquacrop/data/CP_EC-EARTH[CP,RCP45,2041-2060]WG.st"
"aquacrop/data/CP_EC-EARTH[CP,RCP45,2061-2080]WG.dat"
"aquacrop/data/CP_EC-EARTH[CP,RCP85,2021-2040]WG.dat"
"aquacrop/data/CP_EC-EARTH[CP,RCP85,2041-2060]WG.dat"
"aquacrop/data/CP_EC-EARTH[CP,RCP85,2061-2080]WG.dat"
aquacrop/data/MaunaLoaCO2.txt
aquacrop/data/__init__.py
aquacrop/data/brussels_climate.txt
aquacrop/data/brussels_future.txt
aquacrop/data/cambridge_climate.txt
aquacrop/data/champion_climate.txt
aquacrop/data/cmip6_woolpit/CanESM5/CanESM5_historical_1995_2014_52.22057_0.8847.csv
aquacrop/data/cmip6_woolpit/CanESM5/CanESM5_ssp245_2020_2039_52.22057_0.8847.csv
aquacrop/data/cmip6_woolpit/CanESM5/CanESM5_ssp245_2040_2059_52.22057_0.8847.csv
aquacrop/data/cmip6_woolpit/CanESM5/CanESM5_ssp245_2060_2079_52.22057_0.8847.csv
aquacrop/data/cmip6_woolpit/CanESM5/CanESM5_ssp245_2080_2099_52.22057_0.8847.csv
aquacrop/data/cmip6_woolpit/CanESM5/CanESM5_ssp585_2020_2039_52.22057_0.8847.csv
aquacrop/data/cmip6_woolpit/CanESM5/CanESM5_ssp585_2040_2059_52.22057_0.8847.csv
aquacrop/data/cmip6_woolpit/CanESM5/CanESM5_ssp585_2060_2079_52.22057_0.8847.csv
aquacrop/data/cmip6_woolpit/CanESM5/CanESM5_ssp585_2080_2099_52.22057_0.8847.csv
aquacrop/data/cmip6_woolpit/MIROC6/MIROC6_historical_1995_2014_52.221142_0.884217.csv
aquacrop/data/cmip6_woolpit/MIROC6/MIROC6_ssp245_2020_2039_52.221142_0.884217.csv
aquacrop/data/cmip6_woolpit/MIROC6/MIROC6_ssp245_2040_2059_52.221142_0.884217.csv
aquacrop/data/cmip6_woolpit/MIROC6/MIROC6_ssp245_2060_2079_52.221142_0.884217.csv
aquacrop/data/cmip6_woolpit/MIROC6/MIROC6_ssp245_2080_2099_52.221142_0.884217.csv
aquacrop/data/cmip6_woolpit/MIROC6/MIROC6_ssp585_2020_2039_52.221142_0.884217.csv
aquacrop/data/cmip6_woolpit/MIROC6/MIROC6_ssp585_2040_2059_52.221142_0.884217.csv
aquacrop_ss-3.0.7.dev2.dist-info/LICENSE
aquacrop_ss-3.0.7.dev2.dist-info/METADATA
aquacrop_ss-3.0.7.dev2.dist-info/WHEEL
aquacrop_ss-3.0.7.dev2.dist-info/RECORD
