Metadata-Version: 2.1
Name: aquacrop-ss
Version: 3.0.7.dev2
Summary: A copy of aquacrop model based on version 3.0.7, fixed some deprecated warnings.
License: MIT
Author: SongshGeo
Author-email: songshgeo@gmail.com
Requires-Python: >=3.10,<3.12
Classifier: License :: OSI Approved :: MIT License
Classifier: Programming Language :: Python :: 3
Classifier: Programming Language :: Python :: 3.10
Classifier: Programming Language :: Python :: 3.11
Requires-Dist: cffi (==1.16.0)
Requires-Dist: matplotlib (>=3,<4)
Requires-Dist: numba (>=0.56.0)
Requires-Dist: pandas (>=1.3.5)
Requires-Dist: seaborn (>=0,<1)
Requires-Dist: tqdm (>=4.64.0)
